secret_scanning/__init__.py
secret_scanning/scanner.py
secret_scanning/secrets_config.toml
secret_scanning-1.0.3.dist-info/LICENSE
secret_scanning-1.0.3.dist-info/METADATA
secret_scanning-1.0.3.dist-info/WHEEL
secret_scanning-1.0.3.dist-info/top_level.txt
secret_scanning-1.0.3.dist-info/RECORD
